plAIer/__init__.py
plAIer/main.py
plAIer-1.1.2.dist-info/LICENSE.txt
plAIer-1.1.2.dist-info/METADATA
plAIer-1.1.2.dist-info/WHEEL
plAIer-1.1.2.dist-info/top_level.txt
plAIer-1.1.2.dist-info/RECORD
