Metadata-Version: 2.1
Name: plAIer
Version: 1.1.2
Summary: A Python library that uses a reinforcement learning AI to play board games such as Chess, Tic Tac Toe, and Reversi.
Home-page: https://github.com/L-Martin7/plAIer
Download-URL: https://pypi.python.org/pypi/plAIer
Author: L-Martin7
License: BSD 3-Clause "New" or "Revised" License
Project-URL: Source, https://github.com/L-Martin7/plAIer
Project-URL: Issues, https://github.com/L-Martin7/plAIer/issues
Keywords: AI,artificial intelligence,play,game,reinforcement AI,player,board games
Platform: Linux
Platform: macOS
Platform: Windows
License-File: LICENSE.txt
